krypton/__init__.py
krypton/core/prompts/parser_prompts.py
krypton/parser/__init__.py
krypton/parser/base.py
krypton/parser/generic.py
krypton/parser/llm.py
krypton/parser/main.py
krypton/schema.py
krypton/splitter.py
krypton_toolkit-0.1.0.dist-info/METADATA
krypton_toolkit-0.1.0.dist-info/WHEEL
krypton_toolkit-0.1.0.dist-info/RECORD
