Metadata-Version: 2.3
Name: krypton-toolkit
Version: 0.1.0
Summary: Context Engineering Framework for LLMs and Agents
License: Apache-2.0
Author: Varun
Author-email: varun@example.com
Requires-Python: >=3.10,<4.0
Classifier: License :: OSI Approved :: Apache Software License
Classifier: Programming Language :: Python :: 3
Classifier: Programming Language :: Python :: 3.10
Classifier: Programming Language :: Python :: 3.11
Classifier: Programming Language :: Python :: 3.12
Classifier: Programming Language :: Python :: 3.13
Requires-Dist: instructor (>=1.0.0,<2.0.0)
Requires-Dist: litellm (>=1.0.0,<2.0.0)
Requires-Dist: pdfplumber (>=0.11.0,<0.12.0)
Requires-Dist: pydantic (>=2.0,<3.0)
Requires-Dist: pypdf (>=6.4.1,<7.0.0)
Requires-Dist: pytesseract (>=0.3.10,<0.4.0)
